#ifndef BADJVM_OPCODES_H
#define BADJVM_OPCODES_H

#include <cstdint>

static constexpr uint8_t op_nop = 0x00;
static constexpr uint8_t op_aconst_null = 0x01;
static constexpr uint8_t op_iconst_m1 = 0x02;
static constexpr uint8_t op_iconst_0 = 0x03;
static constexpr uint8_t op_iconst_1 = 0x04;
static constexpr uint8_t op_iconst_2 = 0x05;
static constexpr uint8_t op_iconst_3 = 0x06;
static constexpr uint8_t op_iconst_4 = 0x07;
static constexpr uint8_t op_iconst_5 = 0x08;
static constexpr uint8_t op_fconst_0 = 0x0b;
static constexpr uint8_t op_fconst_1 = 0x0c;
static constexpr uint8_t op_fconst_2 = 0x0d;
static constexpr uint8_t op_bipush = 0x10;
static constexpr uint8_t op_sipush = 0x11;
static constexpr uint8_t op_ldc = 0x12;
static constexpr uint8_t op_ldc2_w = 0x14;
static constexpr uint8_t op_iload = 0x15;
static constexpr uint8_t op_dload = 0x18;
static constexpr uint8_t op_iload_0 = 0x1a;
static constexpr uint8_t op_iload_1 = 0x1b;
static constexpr uint8_t op_iload_2 = 0x1c;
static constexpr uint8_t op_iload_3 = 0x1d;
static constexpr uint8_t op_lload_0 = 0x1e;
static constexpr uint8_t op_lload_1 = 0x1f;
static constexpr uint8_t op_lload_2 = 0x20;
static constexpr uint8_t op_lload_3 = 0x21;
static constexpr uint8_t op_fload_0 = 0x22;
static constexpr uint8_t op_fload_1 = 0x23;
static constexpr uint8_t op_fload_2 = 0x24;
static constexpr uint8_t op_fload_3 = 0x25;
static constexpr uint8_t op_dload_0 = 0x26;
static constexpr uint8_t op_dload_1 = 0x27;
static constexpr uint8_t op_dload_2 = 0x28;
static constexpr uint8_t op_dload_3 = 0x29;
static constexpr uint8_t op_aload_0 = 0x2a;
static constexpr uint8_t op_aload_1 = 0x2b;
static constexpr uint8_t op_aload_2 = 0x2c;
static constexpr uint8_t op_aload_3 = 0x2d;
static constexpr uint8_t op_iaload = 0x2e;
static constexpr uint8_t op_caload = 0x34;
static constexpr uint8_t op_aaload = 0x32;
static constexpr uint8_t op_istore = 0x36;
static constexpr uint8_t op_dstore = 0x39;
static constexpr uint8_t op_istore_0 = 0x3b;
static constexpr uint8_t op_istore_1 = 0x3c;
static constexpr uint8_t op_istore_2 = 0x3d;
static constexpr uint8_t op_istore_3 = 0x3e;
static constexpr uint8_t op_lstore_0 = 0x3f;
static constexpr uint8_t op_lstore_1 = 0x40;
static constexpr uint8_t op_lstore_2 = 0x41;
static constexpr uint8_t op_lstore_3 = 0x42;
static constexpr uint8_t op_dstore_0 = 0x47;
static constexpr uint8_t op_dstore_1 = 0x48;
static constexpr uint8_t op_dstore_2 = 0x49;
static constexpr uint8_t op_dstore_3 = 0x4a;
static constexpr uint8_t op_astore_0 = 0x4b;
static constexpr uint8_t op_astore_1 = 0x4c;
static constexpr uint8_t op_astore_2 = 0x4d;
static constexpr uint8_t op_astore_3 = 0x4e;
static constexpr uint8_t op_iastore = 0x4f;
static constexpr uint8_t op_aastore = 0x53;
static constexpr uint8_t op_castore = 0x55;
static constexpr uint8_t op_pop = 0x57;
static constexpr uint8_t op_pop2 = 0x58;
static constexpr uint8_t op_dup = 0x59;
static constexpr uint8_t op_iadd = 0x60;
static constexpr uint8_t op_dadd = 0x63;
static constexpr uint8_t op_isub = 0x64;
static constexpr uint8_t op_dsub = 0x67;
static constexpr uint8_t op_imul = 0x68;
static constexpr uint8_t op_fmul = 0x6a;
static constexpr uint8_t op_idiv = 0x6c;
static constexpr uint8_t op_ddiv = 0x6f;
static constexpr uint8_t op_irem = 0x70;
static constexpr uint8_t op_ishl = 0x78;
static constexpr uint8_t op_ishr = 0x7a;
static constexpr uint8_t op_iushr = 0x7c;
static constexpr uint8_t op_iinc = 0x84;
static constexpr uint8_t op_i2l = 0x85;
static constexpr uint8_t op_i2f = 0x86;
static constexpr uint8_t op_i2d = 0x87;
static constexpr uint8_t op_l2i = 0x88;
static constexpr uint8_t op_l2f = 0x89;
static constexpr uint8_t op_l2d = 0x8a;
static constexpr uint8_t op_f2i = 0x8b;
static constexpr uint8_t op_f2l = 0x8c;
static constexpr uint8_t op_f2d = 0x8d;
static constexpr uint8_t op_d2i = 0x8e;
static constexpr uint8_t op_d2l = 0x8f;
static constexpr uint8_t op_d2f = 0x90;
static constexpr uint8_t op_i2b = 0x91;
static constexpr uint8_t op_i2c = 0x92;
static constexpr uint8_t op_i2s = 0x93;
static constexpr uint8_t op_lcmp = 0x94;
static constexpr uint8_t op_fcmpl = 0x95;
static constexpr uint8_t op_fcmpg = 0x96;
static constexpr uint8_t op_ifeq = 0x99;
static constexpr uint8_t op_ifne = 0x9a;
static constexpr uint8_t op_iflt = 0x9b;
static constexpr uint8_t op_ifge = 0x9c;
static constexpr uint8_t op_ifgt = 0x9d;
static constexpr uint8_t op_ifle = 0x9e;
static constexpr uint8_t op_if_icmpeq = 0x9f;
static constexpr uint8_t op_if_icmpne = 0xa0;
static constexpr uint8_t op_if_icmplt = 0xa1;
static constexpr uint8_t op_if_icmpge = 0xa2;
static constexpr uint8_t op_if_icmpgt = 0xa3;
static constexpr uint8_t op_if_icmple = 0xa4;
static constexpr uint8_t op_goto = 0xa7;
static constexpr uint8_t op_ireturn = 0xac;
static constexpr uint8_t op_dreturn = 0xaf;
static constexpr uint8_t op_areturn = 0xb0;
static constexpr uint8_t op_return = 0xb1;
static constexpr uint8_t op_getstatic = 0xb2;
static constexpr uint8_t op_putstatic = 0xb3;
static constexpr uint8_t op_getfield = 0xb4;
static constexpr uint8_t op_putfield = 0xb5;
static constexpr uint8_t op_invokevirtual = 0xb6;
static constexpr uint8_t op_invokespecial = 0xb7;
static constexpr uint8_t op_invokestatic = 0xb8;
static constexpr uint8_t op_new = 0xbb;
static constexpr uint8_t op_newarray = 0xbc;
static constexpr uint8_t op_anewarray = 0xbd;
static constexpr uint8_t op_arraylength = 0xbe;
static constexpr uint8_t op_monitorenter = 0xc2;
static constexpr uint8_t op_monitorexit = 0xc3;
static constexpr uint8_t op_ifnull = 0xc6;
static constexpr uint8_t op_ifnonnull = 0xc7;

#endif //BADJVM_OPCODES_H
